  {
    "name": "Project Quality",
    "mnemo": "QM_QUALITY",
    "active": "true",
    "children": [
      {
        "name": "Community",
        "mnemo": "QM_COMMUNITY",
        "active": "true",
        "children": [
          {
            "name": "Activity",
            "mnemo": "QM_ACTIVITY",
            "active": "true",
            "children": [
              {
                "name": "Developer ML activity",
                "mnemo": "MLS_DEV_ACTIVITY",
                "value": "xxx"
              },
              {
                "name": "User ML activity",
                "mnemo": "MLS_USR_ACTIVITY",
                "value": "xxx"
              },
              {
                "name": "SCM activity",
                "mnemo": "SCM_ACTIVITY",
                "value": "xxx"
              }
            ]
          },
          {
            "name": "Diversity",
            "mnemo": "QM_DIVERSITY",
            "active": "true",
            "children": [
              {
                "name": "Developer ML diversity",
                "mnemo": "MLS_DEV_DIVERSITY",
                "value": "xxx"
              },
              {
                "name": "User ML diversity",
                "mnemo": "MLS_USR_DIVERSITY",
                "value": "xxx"
              },
              {
                "name": "SCM diversity",
                "mnemo": "SCM_DIVERSITY",
                "value": "xxx"
              }
            ]
          },
          {
            "name": "Responsiveness",
            "mnemo": "QM_RESPONSIVENESS",
            "active": "true",
            "children": [
              {
                "name": "Developer ML responsiveness",
                "mnemo": "MLS_DEV_RESPONSIVENESS",
                "value": "xxx"
              },
              {
                "name": "User ML responsiveness",
                "mnemo": "MLS_USR_RESPONSIVENESS",
                "value": "xxx"
              }
            ]
          },
          {
            "name": "Support",
            "mnemo": "QM_SUPPORT",
            "active": "true",
            "children": [
              {
                "name": "Developer ML support",
                "mnemo": "MLS_DEV_SUPPORT",
                "value": "xxx"
              },
              {
                "name": "Developer ML support",
                "mnemo": "MLS_USR_SUPPORT",
                "value": "xxx"
              }
            ]
          },
          {
            "name": "Installed base",
            "mnemo": "QM_INSTALL_BASE",
            "active": "false",
            "children": [
              {
                "name": "Installations",
                "mnemo": "INSTALL",
                "value": "xxx"
              }
            ]
          }
        ]
      },
      {
        "name": "Process",
        "mnemo": "QM_PROCESS",
        "active": "true",
        "children": [
          {
            "name": "Configuration Management",
            "active": "false",
            "children": [
              {
                "name": "SCM information access",
                "mnemo": "PUB_SCM_INFO",
                "value": "xxx"
              },
              {
                "name": "SCM usage",
                "mnemo": "SCM_USAGE",
                "value": "xxx"
              }
            ]
          },
          {
            "name": "Change Management",
            "active": "false",
            "children": [
              {
                "name": "ITS information access",
                "mnemo": "PUB_ITS_INFO",
                "value": "xxx"
              },
              {
                "name": "ITS usage",
                "mnemo": "ITS_USAGE",
                "value": "xxx"
              }
            ]
          },
          {
            "name": "Intellectual Property Management",
            "active": "false",
            "children": [
              {
                "name": "License identification",
                "mnemo": "LIC",
                "value": "xxx"
              },
              {
                "name": "IP log",
                "mnemo": "IP_LOG",
                "value": "xxx"
              }
            ]
          },
          {
            "name": "Planning Management",
            "active": "false",
            "children": [
              {
                "name": "Plan on time",
                "mnemo": "PLAN_ON_TIME",
                "value": "xxx"
              },
              {
                "name": "Milestones",
                "mnemo": "PLAN_MILESTONES",
                "value": "xxx"
              }
            ]
          },
          {
            "name": "Test Management",
            "active": "false",
            "children": [
              {
                "name": "Test coverage",
                "mnemo": "TST_COV",
                "value": "xxx"
              },
              {
                "name": "Number of tests",
                "mnemo": "TST_VOL",
                "value": "xxx"
              },
              {
                "name": "Test success rate",
                "mnemo": "TST_SUCCESS",
                "value": "xxx"
              }
            ]
          }
        ]
      },
      {
        "name": "Product",
        "mnemo": "QM_PRODUCT",
        "active": "false",
            "children": [
          {
            "name": "Analysability",
            "active": "true",
            "children": [
              {
                "name": "Code size",
                "mnemo": "CODE_SIZE",
                "value": "xxx",
                "active": "true"
              },
              {
                "name": "Access points",
                "mnemo": "ALL_DATA",
                "value": "xxx"
              },
              {
                "name": "Code complexity",
                "mnemo": "CPX",
                "value": "xxx"
              },
              {
                "name": "Code documentation",
                "mnemo": "CODE_DOC",
                "value": "xxx"
              },
              {
                "name": "Analysability practices",
                "mnemo": "PRACTICES_ANA",
                "value": "xxx"
              }
            ]
          },
          {
            "name": "Changeability",
            "active": "true",
            "children": [
              {
                "name": "Public access points",
                "mnemo": "PUBLIC_DATA",
                "value": "xxx"
              },
              {
                "name": "Code complexity",
                "mnemo": "CPX",
                "value": "xxx"
              },
              {
                "name": "Code cloning",
                "mnemo": "CODE_CLONE",
                "value": "xxx"
              },
              {
                "name": "Changeability practices",
                "mnemo": "PRACTICES_CHA",
                "value": "xxx"
              }
            ]
          },
          {
            "name": "Reliability",
            "active": "true",
            "children": [
              {
                "name": "Public access points",
                "mnemo": "PUBLIC_DATA",
                "value": "xxx"
              },
              {
                "name": "Code complexity",
                "mnemo": "CPX",
                "value": "xxx"
              },
              {
                "name": "SCM stability",
                "mnemo": "SCM_STABILITY",
                "value": "xxx"
              },
              {
                "name": "ITS reliability",
                "mnemo": "ITS_REL",
                "value": "xxx"
              },
              {
                "name": "Reliability practices",
                "mnemo": "PRACTICES_REL",
                "value": "xxx"
              }
            ]
          },
          {
            "name": "Reusability",
            "mnemo": "QM_REUSABILITY",
            "active": "true",
            "children": [
              {
                "name": "Public access points",
                "mnemo": "PUBLIC_DATA",
                "value": "xxx"
              },
              {
                "name": "Test coverage",
                "mnemo": "TST_COV",
                "value": "xxx"
              },
              {
                "name": "Code documentation",
                "mnemo": "CODE_DOC",
                "value": "xxx"
              },
              {
                "name": "Reusability practices",
                "mnemo": "PRACTICES_REU",
                "value": "xxx"
              }
            ]
          }
        ]
      }
    ]
  }
