  {
    "name": "Project Quality",
    "children": [
      {
        "name": "Community",
        "children": [
          {
            "name": "Activity",
            "value": "3" 
          },
          {
            "name": "Diversity",
            "value": "3"
          },
          {
            "name": "Responsiveness",
            "value": "3"
          },
          {
            "name": "Support",
            "value": "3"
          },
          {
            "name": "Installed base",
            "value": "3"
          }
        ]
      },
      {
        "name": "Process",
        "children": [
          {
            "name": "CCM Management",
            "value": "3"
          },
          {
            "name": "Intellectual Property Management",
            "value": "3"
          },
          {
            "name": "Planning Management",
            "value": "3"
          },
          {
            "name": "Test Management",
            "value": "3"
          }
        ]
      },
      {
        "name": "Product",
        "children": [
          {
            "name": "Analysability",
            "value": "3"
          },
          {
            "name": "Changeability",
            "value": "3"
          },
          {
            "name": "Reliability",
            "value": "3"
          },
          {
            "name": "Reusability",
            "value": "3"
          }
        ]
      }
    ]
  }
